{"stat": {"question_id": 188, "question__article__live": true, "question__article__slug": "best-time-to-buy-and-sell-stock-iv", "question__article__has_video_solution": false, "question__title": "Best Time to Buy and Sell Stock IV", "question__title_slug": "best-time-to-buy-and-sell-stock-iv", "question__hide": false, "total_acs": 181769, "total_submitted": 600648, "frontend_question_id": 188, "is_new_question": false}, "status": null, "difficulty": {"level": 3}, "paid_only": false, "is_favor": false, "frequency": 0, "progress": 0}