{"stat": {"question_id": 990, "question__article__live": true, "question__article__slug": "verifying-an-alien-dictionary", "question__article__has_video_solution": false, "question__title": "Verifying an Alien Dictionary", "question__title_slug": "verifying-an-alien-dictionary", "question__hide": false, "total_acs": 234346, "total_submitted": 446948, "frontend_question_id": 953, "is_new_question": false}, "status": null, "difficulty": {"level": 1}, "paid_only": false, "is_favor": false, "frequency": 0, "progress": 0}