{"stat": {"question_id": 1761, "question__article__live": true, "question__article__slug": "count-sorted-vowel-strings", "question__article__has_video_solution": false, "question__title": "Count Sorted Vowel Strings", "question__title_slug": "count-sorted-vowel-strings", "question__hide": false, "total_acs": 51719, "total_submitted": 68682, "frontend_question_id": 1641, "is_new_question": false}, "status": null, "difficulty": {"level": 2}, "paid_only": false, "is_favor": false, "frequency": 0, "progress": 0}