{"stat": {"question_id": 1007, "question__article__live": true, "question__article__slug": "numbers-with-same-consecutive-differences", "question__article__has_video_solution": false, "question__title": "Numbers With Same Consecutive Differences", "question__title_slug": "numbers-with-same-consecutive-differences", "question__hide": false, "total_acs": 43287, "total_submitted": 95416, "frontend_question_id": 967, "is_new_question": false}, "status": null, "difficulty": {"level": 2}, "paid_only": false, "is_favor": false, "frequency": 0, "progress": 0}