{"stat": {"question_id": 1482, "question__article__live": null, "question__article__slug": null, "question__article__has_video_solution": null, "question__title": "How Many Numbers Are Smaller Than the Current Number", "question__title_slug": "how-many-numbers-are-smaller-than-the-current-number", "question__hide": false, "total_acs": 198539, "total_submitted": 230914, "frontend_question_id": 1365, "is_new_question": false}, "status": null, "difficulty": {"level": 1}, "paid_only": false, "is_favor": false, "frequency": 0, "progress": 0}