{"stat": {"question_id": 1704, "question__article__live": null, "question__article__slug": null, "question__article__has_video_solution": null, "question__title": "Special Positions in a Binary Matrix", "question__title_slug": "special-positions-in-a-binary-matrix", "question__hide": false, "total_acs": 21990, "total_submitted": 34355, "frontend_question_id": 1582, "is_new_question": false}, "status": null, "difficulty": {"level": 1}, "paid_only": false, "is_favor": false, "frequency": 0, "progress": 0}