{"stat": {"question_id": 1488, "question__article__live": null, "question__article__slug": null, "question__article__has_video_solution": null, "question__title": "Sort Integers by The Power Value", "question__title_slug": "sort-integers-by-the-power-value", "question__hide": false, "total_acs": 32159, "total_submitted": 45525, "frontend_question_id": 1387, "is_new_question": false}, "status": null, "difficulty": {"level": 2}, "paid_only": false, "is_favor": false, "frequency": 0, "progress": 0}